executive/__init__.py
executive/after.py
executive/before.py
executive/groupby.py
executive/trim.py
executive-0.0.1.dist-info/METADATA
executive-0.0.1.dist-info/WHEEL
executive-0.0.1.dist-info/entry_points.txt
executive-0.0.1.dist-info/top_level.txt
executive-0.0.1.dist-info/RECORD
