Metadata-Version: 2.1
Name: executive
Version: 0.0.1
Summary: An ode to the exec system call.
Author-email: Jason Wilkes <notarealdeveloper@gmail.com>
Project-URL: source, https://github.com/notarealdeveloper/executive
Project-URL: download, https://pypi.org/project/executive/#files
Requires-Dist: pytest
Requires-Dist: pandas
Requires-Dist: signalhandlers
